{
  "Top": 96,
  "Left": 50,
  "Width": 0,
  "Height": 0,
  "SourceTypeName": "Class",
  "SourceId": "35b78e14-c8f5-49b2-80f1-79dab4b738dd",
  "IsOpen": true,
  "ReferenceKind": null,
  "ReferencedElementType": "Class",
  "ReferencedElementId": "35b78e14-c8f5-49b2-80f1-79dab4b738dd",
  "ReferencedElementName": "Account",
  "SchemaVersion": "1.0",
  "MementoClassname": "ShapeMemento",
  "Id": "ED8A27A87E94CA29E045D69665C2A0DA",
  "ExternalId": null,
  "TypeName": "Shape",
  "Name": "Account",
  "Description": null,
  "ParentTypeName": "Diagram",
  "ParentId": "59136cf9-257c-4bd4-801d-a51aad0666d5_DIAGRAM",
  "CreationMethod": "Undefined",
  "LifeCycleState": "Active",
  "Tags": null
}